ascvd/__init__.py
ascvd-0.5.dist-info/DESCRIPTION.rst
ascvd-0.5.dist-info/METADATA
ascvd-0.5.dist-info/RECORD
ascvd-0.5.dist-info/WHEEL
ascvd-0.5.dist-info/metadata.json
ascvd-0.5.dist-info/top_level.txt
