Metadata-Version: 2.0
Name: ascvd
Version: 0.5
Summary: Module for calculating ASCVD 10-year estimate
Home-page: https://github.com/brandones/ascvd
Author: Brandon Istenes
Author-email: brandonesbox@gmail.com
License: UNKNOWN
Project-URL: Source, https://github.com/brandones/ascvd
Platform: UNKNOWN
